text_vectors
