Metadata-Version: 1.0
Name: text-vectors
Version: 0.2.0
Summary: Create text vectors in a robust way using GloVe or pre-built vectors only
Home-page: https://github.com/chappers/text-vectors
Author: Chapman Siu
Author-email: chapm0n.siu@gmail.com
License: UNKNOWN
Keywords: text vectors
Platform: UNKNOWN
